controller.vhd
library ieee;
use ieee.std_logic_1164.all;
use work.risc16_package.all;

entity controller is
	port( opcode    : in std_logic_vector(2 downto 0);
		  RegWrite  : out std_logic;
		  ALUSrc    : out std_logic;
		  ExtSrc    : out std_logic;
          MemWrite  : out std_logic;
		  MemRead	: out std_logic;
		  MemtoReg  : out std_logic;
		  Branch    : out std_logic;
		  JumpL     : out std_logic);
end controller;

architecture bhv of controller is

begin

 process (opcode)
 begin 	
	case opcode is

		when ADD  => RegWrite <= '1';
					 ALUSrc   <= '0';
					 ExtSrc   <= 'X';
					 MemWrite <= '0';
					 MemRead  <= '0';
					 MemtoReg <= '1';
					 Branch   <= '0';
					 JumpL    <= '0';
	
		when ADDI => RegWrite <= '1';
				     ALUSrc   <= '1';
					 ExtSrc   <= '0';
					 MemWrite <= '0';
					 MemRead  <= '0';
					 MemtoReg <= '1';
					 Branch   <= '0';
					 JumpL    <= '0';

		when NANDi=> RegWrite <= '1';
				     ALUSrc   <= '0';
					 ExtSrc   <= '0';
					 MemWrite <= '0';
					 MemRead  <= '0';
					 MemtoReg <= '1';
					 Branch   <= '0';
					 JumpL    <= '0';

		when LUI =>  RegWrite <= '1';
					 ALUSrc   <= '1';
					 ExtSrc   <= '1';
					 MemWrite <= '0';
					 MemRead  <= '0';
					 MemtoReg <= '1';
					 Branch   <= '0';
					 JumpL    <= '0';

		when SW  =>  RegWrite <= '0';
					 ALUSrc   <= '1';
					 ExtSrc   <= '0';
					 MemWrite <= '1';
					 MemRead  <= '0';
					 MemtoReg <= 'X';
					 Branch   <= '0';
					 JumpL    <= '0';
					 
		when LW  =>  RegWrite <= '1';
					 ALUSrc   <= '1';
					 ExtSrc   <= '0';
					 MemWrite <= '0';
					 MemRead  <= '1';
					 MemtoReg <= '0';
					 Branch   <= '0';
					 JumpL    <= '0';

		when BEQ  => RegWrite <= '0';
					 ALUSrc   <= '0';
					 ExtSrc   <= '0';
					 MemWrite <= '0';
					 MemRead  <= '0';
					 MemtoReg <= 'X';
					 Branch   <= '1';
					 JumpL    <= '0';

		when JALR => RegWrite <= '0';
					 ALUSrc   <= '0';
					 ExtSrc   <= '0';
					 MemWrite <= '0';
					 MemRead  <= '0';
					 MemtoReg <= 'X';
					 Branch   <= '1';
					 JumpL    <= '1';

		when others => JumpL <= '0';
					   Branch <= '0';		
	end case;
   end process;

end bhv;

risc16/fake_memory.vhd
library ieee;
use ieee.std_logic_1164.all;
use ieee.std_logic_unsigned.all;

entity fake_memory is

	port( clk	   : in std_logic;
		  reset	   : in std_logic;
		  MemWrite : in std_logic;
		  MemRead  : in std_logic;
		  addr     : in std_logic_vector(15 downto 0);
		  write	   : in std_logic_vector(15 downto 0);
		  read	   : out std_logic_vector(15 downto 0));
end fake_memory;


architecture bhv of fake_memory is

signal single_register : std_logic_vector(15 downto 0);

begin

write_memory : process(MemWrite,addr,clk,reset)
	--nao faz uso de addr, escreve sempre no mesmo registrador
	begin
		if reset = '1' then
			single_register <= "0000000000000000";
		elsif ((clk'event  and clk='1') and (MemWrite='1')) then
			single_register <= write;
		end if;
	end process write_memory;

read_memory : process(MemRead)
	begin
		if MemRead ='1' then
			read <= single_register;
		end if;
	end process read_memory;


end bhv;

nbitsmux.vhd
library ieee;
use ieee.std_logic_1164.all;


entity nbitsmux is
	generic (N: integer:=8);
    port(  sel 	   : in std_logic;
 		   a, b	   : in std_logic_vector(N-1 downto 0);
		   mux_out : out std_logic_vector(N-1 downto 0);
        );
end nbitsmux;

architecture bhv of nbitsmux is
begin

    mux_out <= a when sel = '0' else
               b;
end bhv;

risc16/alu.vhd
library ieee;
use ieee.std_logic_1164.all;
use ieee.std_logic_signed.all;
use ieee.numeric_std.all;

entity alu is
port(  alu_control : in std_logic_vector(3 downto 0);
	   zero 	   : out std_logic;
	   a		   : in std_logic_vector(15 downto 0);
	   b		   : in std_logic_vector(15 downto 0);
	   alu_out 	   : out std_logic_vector(15 downto 0));
end alu;

architecture bhv of alu is

signal slt : std_logic;
signal alu_out_sig : std_logic_vector(15 downto 0);

begin

	alu_out <= alu_out_sig;


	slt_setter : process(a,b) is
		begin
			if (conv_integer(a) > conv_integer(b)) then 
				slt <= '1';
			elsif (conv_integer(a) < conv_integer(b)) then 
				slt <= '0';
			else
				slt <= 'Z';
			end if;
	end process slt_setter;

	with alu_out_sig select

		zero <= '1' when "0000000000000000",
				'0' when others;


	with alu_control select
		alu_out_sig <= a + b    when "0000",
				       a nand b when "0001",
				       a and b  when "0010",
				       a - b    when "0101",
				       "000000000000000"&slt when "0111",
					   b(15 downto 6) & "000000" when "1000", -- lui
				       a when others;

end bhv;

registers.vhd
library ieee;
use ieee.std_logic_1164.all;
use ieee.std_logic_unsigned.all;

entity registers is
port( clk        : in std_logic;
	  reset      : in std_logic;
	  RegWrite 	 : in std_logic;
	  rs_address : in std_logic_vector(2 downto 0);
	  rt_address : in std_logic_vector(2 downto 0);
	  rd_address : in std_logic_vector(2 downto 0);
	  write_data : in std_logic_vector(15 downto 0);
	  data_1	 : out std_logic_vector(15 downto 0);
	  data_2	 : out std_logic_vector(15 downto 0);
	  data_rd    : out std_logic_vector(15 downto 0));
end registers;

architecture bhv of registers is

type BANKREG is array(0 to 7) of std_logic_vector(15 downto 0);

signal bank_register : BANKREG;

begin

data_1 <= bank_register(conv_integer(rs_address));
data_2 <= bank_register(conv_integer(rt_address));
data_rd <= bank_register(conv_integer(rd_address));

write_bank_register : process (clk,RegWrite,reset)
	begin
		if reset = '1' then
			bank_register(0) <= "0000000000000000"; -- r0 constante
			bank_register(1) <= "0000000000000100"; -- r1
			bank_register(2) <= "0000000000000010"; -- r2 
			bank_register(3) <= "0000000000010000"; -- r3 
			bank_register(4) <= "0000000000000000"; -- r4 
			bank_register(5) <= "0000000000000000"; -- r5 
			bank_register(6) <= "0000000000000000"; -- r6 
			bank_register(7) <= "0000000000000000"; -- r7
		elsif ((clk'event and clk ='1') and (RegWrite = '1')) then
			if (rd_address(2 downto 0) = 0) then
				bank_register(0) <= "0000000000000000";
			else
				bank_register(conv_integer(rd_address(2 downto 0))) <= write_data;
			end if;
		end if;
	end process write_bank_register;

end bhv;

-- reads to register 0 always returns 0

datapath.vhd
library ieee;
use ieee.std_logic_1164.all;
use ieee.numeric_std.all;
use work.risc16_package.all;


entity datapath is
	port( clk  		: in std_logic;
		  reset     : in std_logic;
		  instruction : in std_logic_vector(15 downto 0);
		  RegWrite  : in std_logic;
		  ALUSrc    : in std_logic;
		  ExtSrc    : in std_logic;
		  MemWrite  : in std_logic;
		  MemRead	: in std_logic;
		  MemtoReg  : in std_logic;
		  Branch 	: in std_logic; 
		  JumpL     : in std_logic);
end datapath;


architecture bhv of datapath is 


signal opcode, regA_address, regB_address, regC_address : std_logic_vector(2 downto 0);
signal imm7 			     : std_logic_vector(6 downto 0);
signal imm10				 : std_logic_vector(9 downto 0);
signal extended_imm7 		 : std_logic_vector(15 downto 0);
signal extended_imm10		 : std_logic_vector(15 downto 0);
signal extended_imm			 : std_logic_vector(15 downto 0);
signal alu_control 			 : std_logic_vector(3 downto 0);
signal data_to_register 	 : std_logic_vector(15 downto 0);
signal data_to_register_final: std_logic_vector(15 downto 0);
signal zero			 		 : std_logic;
signal alu_out 				 : std_logic_vector(15 downto 0);
signal data1_from_registers  : std_logic_vector(15 downto 0); 
signal data2_from_mux_to_alu : std_logic_vector(15 downto 0);
signal data2_from_registers  : std_logic_vector(15 downto 0);
signal data_from_rd   : std_logic_vector(15 downto 0);
signal alu_input2 : std_logic_vector(15 downto 0);

signal data_from_memory : std_logic_vector(15 downto 0);

signal PC_register : std_logic_vector(15 downto 0) := INITIAL_VALUE;
signal from_mux_to_pc : std_logic_vector(15 downto 0);
signal from_mux_to_pc_final : std_logic_vector(15 downto 0);
signal PC_add1_out : std_logic_vector(15 downto 0);
signal PC_add_imm_out : std_logic_vector(15 downto 0);
signal PCSrc	   : std_logic := '0';


begin

--sinal instruction é alimentado pela instruction memory
--que é acessada por PC
--mas nessa implementação instruction é uma entrada alimentada pelo testbench
opcode 	   	   <= instruction(15 downto 13);
regA_address   <= instruction(12 downto 10);
regB_address   <= instruction(9 downto 7);
regC_address   <= instruction(2 downto 0);
imm7   		   <= instruction(6 downto 0);
imm10  		   <= instruction(9 downto 0);



risc16_registers : registers
	port map ( clk 		  => clk,
			   reset 	  => reset,
			   RegWrite   => RegWrite,
			   rs_address => regB_address,
			   rt_address => regC_address,
			   rd_address => regA_address,
			   write_data => data_to_register_final,
			   data_1     => data1_from_registers,
			   data_2     => data2_from_registers,
			   data_rd    => data_from_rd
	);

--sign extension
extended_imm7  <= std_logic_vector(resize(signed(imm7), extended_imm7'length)); 

extended_imm10 <= std_logic_vector(resize(signed(imm10), extended_imm10'length));

mux_to_extended : nbitsmux
	generic map (N => 16)
	port map ( sel => ExtSrc,
			   a   => extended_imm7,
			   b   => extended_imm10,
			   mux_out => extended_imm
	);

mux_to_alu_source : nbitsmux
	generic map (N => 16)
	port map ( sel => ALUSrc,
			   a   => data2_from_registers,
			   b   => extended_imm,
			   mux_out => data2_from_mux_to_alu
	);

mux_to_alu : nbitsmux
	generic map (N => 16)
	port map (  sel => Branch,
				a  => data2_from_mux_to_alu,
				b  => data_from_rd,
				mux_out => alu_input2
	);

alu_main : alu
	port map( alu_control => alu_control, 
			  zero 		  => zero,	
		      a			  => data1_from_registers,
			  b 		  => alu_input2,
			  alu_out     => alu_out
	);


PC_add1 : alu
	port map (alu_control => "0000",
			  a           => PC_register,
			  b			  => "0000000000000001",
			  alu_out     => PC_add1_out
	);

PC_add_imm : alu
	port map (alu_control => "0000",
			  a	=> PC_add1_out,
			  b => extended_imm,
			  alu_out => PC_add_imm_out
	);

with alu_out select
	zero <= '1' when "0000000000000000",
			'0' when others;

PCSrc <= Branch and zero;

mux_to_PC : nbitsmux
	generic map (N => 16)
	port map ( sel => PCSrc,
			   a   => PC_add1_out,
			   b   => PC_add_imm_out,
			   mux_out => from_mux_to_pc
	);

mux_to_JumpL : nbitsmux
	generic map (N => 16)
	port map ( sel => JumpL,
			   a => from_mux_to_pc,
			   b => data1_from_registers,
			   mux_out => from_mux_to_pc_final
	);


write_PC : process(clk)
	begin
		if(clk'event and clk='1') then
		  PC_register <= from_mux_to_pc_final;
		end if;
	end process;



--data_to_register <= alu_out;
mux_data_src_ALUxMEM : nbitsmux
	generic map (N => 16)
	port map ( sel => MemToReg,
			   a   => data_from_memory,
			   b   => alu_out,
			   mux_out => data_to_register
	);

mux_data_to_registers : nbitsmux
	generic map (N => 16)
	port map ( sel => JumpL,
			   a => data_to_register,
			   b => PC_add1_out,
			   mux_out => data_to_register_final 
	);



memory : fake_memory
	port map ( clk => clk,
			   reset => reset,
			   MemWrite => MemWrite,
			   MemRead => MemRead,
			   addr => alu_out,
			   write => data_from_rd,
			   read  => data_from_memory
	);



--opcode define a função da ula
with opcode select
	alu_control  <= "0000" when "000", --add 
					"0000" when "001", --addi
					"0001" when "010", --nand
					"1000" when "011", --lui
					"0000" when "100", --sw
					"0000" when "101", --lw
					"0101" when "110", --beq
					"0000" when "111", --jalr
					"0000" when others;

end bhv;

risc16/testbench_datapath.vhd
library ieee;
use ieee.std_logic_1164.all;
use work.risc16_package.all;

entity testbench_datapath is
end testbench_datapath;

architecture bhv of testbench_datapath is

signal clk 			:  std_logic := '0'; 
signal reset 	    :  std_logic := '0';
signal finished     :  std_logic := '0';
signal instruction  :  std_logic_vector(15 downto 0);
signal RegWrite 	:  std_logic;
signal ALUSrc 	 	:  std_logic;
signal ExtSrc 		:  std_logic;
signal MemWrite		:  std_logic;
signal MemRead		:  std_logic;
signal MemtoReg		:  std_logic;
signal Branch 		:  std_logic;
signal JumpL 		:  std_logic;
signal opcode       :  std_logic_vector(2 downto 0);

begin

opcode <= instruction(15 downto 13);

risc_datapath : datapath 
	port map(clk,reset,instruction,RegWrite,ALUSrc,ExtSrc,MemWrite,MemRead,MemtoReg,Branch,JumpL);


risc_controller : controller
	port map (opcode,RegWrite,ALUSrc,ExtSrc,MemWrite,MemRead,MemtoReg,Branch,JumpL);


process(clk)
 begin
 	clk <= not clk after 60 ns when finished /= '1' else '0';
end process;

process
 begin
 	wait for 30 ns;
	reset <= '1';
	wait for 30 ns;
	reset <= '0';
	wait;  -- suspende o processo em definitivo
end process;

process
 begin
 	wait for 180 ns;	
	-- (RRR) op rA rB "0000" rC
	-- (RRI) op rA rB imm7
	-- (RI)  op rA imm10

	--R0=0 R1=4 R2=2 R3=16 R4-R7=0

	instruction <= SW&R2&R0&"0000000";
	wait for 120 ns;

	instruction <= LW&R6&R0&"0000000";
	wait for 120 ns;

	instruction <= ADD&R7&R6&"0000"&R2;
	wait for 120 ns;

	instruction <= BEQ&R0&R5&"0010000";
	wait for 120 ns;

	instruction <= JALR&R1&R0&"0000000";
	wait for 120 ns;

	instruction <= LUI&R2&"1111111111";
	wait for 120 ns;

	instruction <= SW&R2&R7&"1111111";
	wait for 120 ns;

	instruction <= LW&R6&R0&"0100000";
	wait for 120 ns;

	instruction <= ADD&R1&R2&"0000"&R3;
    wait for 120 ns; 

	instruction <= ADDI&R1&R2&"0100000"; 
	wait for 120 ns;

	instruction <= NANDi&R2&R5&"0000"&R6; 
	wait for 120 ns;

	instruction <= BEQ&R0&R7&"0100000";
	wait for 120 ns;

	instruction <= LUI&R4&"1011011011";
	wait for 120 ns;
/*
	instruction <= JALR&R7&R1&"0000000";	
	wait for 120 ns;

	instruction <= NANDi&R2&R5&"0000"&R6; 
	wait for 120 ns;

	instruction <= SW&R7&R0&"1111111";
	wait for 120 ns;

	instruction <= ADD&R3&R7&"0000"&R1;
    wait for 120 ns; 

	instruction <= LW&R6&R0&"0100000";
	wait for 120 ns;
*/
	finished <= '1';
	wait;
	
end process;

end bhv;

risc16/tb.vcd
$date
  Wed Apr 20 20:35:08 2022
$end
$version
  GHDL v0
$end
$timescale
  1 fs
$end
$scope module standard $end
$upscope $end
$scope module textio $end
$upscope $end
$scope module std_logic_1164 $end
$upscope $end
$scope module risc16_package $end
$upscope $end
$scope module numeric_std $end
$upscope $end
$scope module std_logic_arith $end
$upscope $end
$scope module std_logic_unsigned $end
$upscope $end
$scope module std_logic_signed $end
$upscope $end
$scope module testbench_datapath $end
$var reg 1 ! clk $end
$var reg 1 " reset $end
$var reg 1 # finished $end
$var reg 16 $ instruction[15:0] $end
$var reg 1 % regwrite $end
$var reg 1 & alusrc $end
$var reg 1 ' extsrc $end
$var reg 1 ( memwrite $end
$var reg 1 ) memread $end
$var reg 1 * memtoreg $end
$var reg 1 + branch $end
$var reg 1 , jumpl $end
$var reg 3 - opcode[2:0] $end
$scope module risc_datapath $end
$var reg 1 . clk $end
$var reg 1 / reset $end
$var reg 16 0 instruction[15:0] $end
$var reg 1 1 regwrite $end
$var reg 1 2 alusrc $end
$var reg 1 3 extsrc $end
$var reg 1 4 memwrite $end
$var reg 1 5 memread $end
$var reg 1 6 memtoreg $end
$var reg 1 7 branch $end
$var reg 1 8 jumpl $end
$var reg 3 9 opcode[2:0] $end
$var reg 3 : rega_address[2:0] $end
$var reg 3 ; regb_address[2:0] $end
$var reg 3 < regc_address[2:0] $end
$var reg 7 = imm7[6:0] $end
$var reg 10 > imm10[9:0] $end
$var reg 16 ? extended_imm7[15:0] $end
$var reg 16 @ extended_imm10[15:0] $end
$var reg 16 A extended_imm[15:0] $end
$var reg 4 B alu_control[3:0] $end
$var reg 16 C data_to_register[15:0] $end
$var reg 16 D data_to_register_final[15:0] $end
$var reg 1 E zero $end
$var reg 16 F alu_out[15:0] $end
$var reg 16 G data1_from_registers[15:0] $end
$var reg 16 H data2_from_mux_to_alu[15:0] $end
$var reg 16 I data2_from_registers[15:0] $end
$var reg 16 J data_from_rd[15:0] $end
$var reg 16 K alu_input2[15:0] $end
$var reg 16 L data_from_memory[15:0] $end
$var reg 16 M pc_register[15:0] $end
$var reg 16 N from_mux_to_pc[15:0] $end
$var reg 16 O from_mux_to_pc_final[15:0] $end
$var reg 16 P pc_add1_out[15:0] $end
$var reg 16 Q pc_add_imm_out[15:0] $end
$var reg 1 R pcsrc $end
$scope module risc16_registers $end
$var reg 1 S clk $end
$var reg 1 T reset $end
$var reg 1 U regwrite $end
$var reg 3 V rs_address[2:0] $end
$var reg 3 W rt_address[2:0] $end
$var reg 3 X rd_address[2:0] $end
$var reg 16 Y write_data[15:0] $end
$var reg 16 Z data_1[15:0] $end
$var reg 16 [ data_2[15:0] $end
$var reg 16 \ data_rd[15:0] $end
$comment bank_register is not handled $end
$upscope $end
$scope module mux_to_extended $end
$var reg 1 ] sel $end
$var reg 16 ^ a[15:0] $end
$var reg 16 _ b[15:0] $end
$var reg 16 ` mux_out[15:0] $end
$upscope $end
$scope module mux_to_alu_source $end
$var reg 1 a sel $end
$var reg 16 b a[15:0] $end
$var reg 16 c b[15:0] $end
$var reg 16 d mux_out[15:0] $end
$upscope $end
$scope module mux_to_alu $end
$var reg 1 e sel $end
$var reg 16 f a[15:0] $end
$var reg 16 g b[15:0] $end
$var reg 16 h mux_out[15:0] $end
$upscope $end
$scope module alu_main $end
$var reg 4 i alu_control[3:0] $end
$var reg 1 j zero $end
$var reg 16 k a[15:0] $end
$var reg 16 l b[15:0] $end
$var reg 16 m alu_out[15:0] $end
$var reg 1 n slt $end
$var reg 16 o alu_out_sig[15:0] $end
$upscope $end
$scope module pc_add1 $end
$var reg 4 p alu_control[3:0] $end
$var reg 1 q zero $end
$var reg 16 r a[15:0] $end
$var reg 16 s b[15:0] $end
$var reg 16 t alu_out[15:0] $end
$var reg 1 u slt $end
$var reg 16 v alu_out_sig[15:0] $end
$upscope $end
$scope module pc_add_imm $end
$var reg 4 w alu_control[3:0] $end
$var reg 1 x zero $end
$var reg 16 y a[15:0] $end
$var reg 16 z b[15:0] $end
$var reg 16 { alu_out[15:0] $end
$var reg 1 | slt $end
$var reg 16 } alu_out_sig[15:0] $end
$upscope $end
$scope module mux_to_pc $end
$var reg 1 !" sel $end
$var reg 16 "" a[15:0] $end
$var reg 16 #" b[15:0] $end
$var reg 16 $" mux_out[15:0] $end
$upscope $end
$scope module mux_to_jumpl $end
$var reg 1 %" sel $end
$var reg 16 &" a[15:0] $end
$var reg 16 '" b[15:0] $end
$var reg 16 (" mux_out[15:0] $end
$upscope $end
$scope module mux_data_src_aluxmem $end
$var reg 1 )" sel $end
$var reg 16 *" a[15:0] $end
$var reg 16 +" b[15:0] $end
$var reg 16 ," mux_out[15:0] $end
$upscope $end
$scope module mux_data_to_registers $end
$var reg 1 -" sel $end
$var reg 16 ." a[15:0] $end
$var reg 16 /" b[15:0] $end
$var reg 16 0" mux_out[15:0] $end
$upscope $end
$scope module memory $end
$var reg 1 1" clk $end
$var reg 1 2" reset $end
$var reg 1 3" memwrite $end
$var reg 1 4" memread $end
$var reg 16 5" addr[15:0] $end
$var reg 16 6" write[15:0] $end
$var reg 16 7" read[15:0] $end
$var reg 16 8" single_register[15:0] $end
$upscope $end
$upscope $end
$scope module risc_controller $end
$var reg 3 9" opcode[2:0] $end
$var reg 1 :" regwrite $end
$var reg 1 ;" alusrc $end
$var reg 1 <" extsrc $end
$var reg 1 =" memwrite $end
$var reg 1 >" memread $end
$var reg 1 ?" memtoreg $end
$var reg 1 @" branch $end
$var reg 1 A" jumpl $end
$upscope $end
$upscope $end
$enddefinitions $end
#0
0!
0"
0#
bUUUUUUUUUUUUUUUU $
U%
U&
U'
U(
U)
U*
0+
0,
bUUU -
0.
0/
bUUUUUUUUUUUUUUUU 0
U1
U2
U3
U4
U5
U6
07
08
bUUU 9
bUUU :
bUUU ;
bUUU <
bUUUUUUU =
bUUUUUUUUUU >
bUUUUUUUUUUUUUUUU ?
bUUUUUUUUUUUUUUUU @
bUUUUUUUUUUUUUUUU A
b0000 B
bXXXXXXXXXXXXXXXX C
bXXXXXXXXXXXXXXXX D
0E
bXXXXXXXXXXXXXXXX F
bUUUUUUUUUUUUUUUU G
bUUUUUUUUUUUUUUUU H
bUUUUUUUUUUUUUUUU I
bUUUUUUUUUUUUUUUU J
bUUUUUUUUUUUUUUUU K
bUUUUUUUUUUUUUUUU L
b0000000000000000 M
b0000000000000001 N
b0000000000000001 O
b0000000000000001 P
bXXXXXXXXXXXXXXXX Q
0R
0S
0T
UU
bUUU V
bUUU W
bUUU X
bXXXXXXXXXXXXXXXX Y
bUUUUUUUUUUUUUUUU Z
bUUUUUUUUUUUUUUUU [
bUUUUUUUUUUUUUUUU \
U]
bUUUUUUUUUUUUUUUU ^
bUUUUUUUUUUUUUUUU _
bUUUUUUUUUUUUUUUU `
Ua
bUUUUUUUUUUUUUUUU b
bUUUUUUUUUUUUUUUU c
bUUUUUUUUUUUUUUUU d
0e
bUUUUUUUUUUUUUUUU f
bUUUUUUUUUUUUUUUU g
bUUUUUUUUUUUUUUUU h
b0000 i
0j
bUUUUUUUUUUUUUUUU k
bUUUUUUUUUUUUUUUU l
bXXXXXXXXXXXXXXXX m
Zn
bXXXXXXXXXXXXXXXX o
b0000 p
0q
b0000000000000000 r
b0000000000000001 s
b0000000000000001 t
0u
b0000000000000001 v
b0000 w
0x
b0000000000000001 y
bUUUUUUUUUUUUUUUU z
bXXXXXXXXXXXXXXXX {
1|
bXXXXXXXXXXXXXXXX }
0!"
b0000000000000001 ""
bXXXXXXXXXXXXXXXX #"
b0000000000000001 $"
0%"
b0000000000000001 &"
bUUUUUUUUUUUUUUUU '"
b0000000000000001 ("
U)"
bUUUUUUUUUUUUUUUU *"
bXXXXXXXXXXXXXXXX +"
bXXXXXXXXXXXXXXXX ,"
0-"
bXXXXXXXXXXXXXXXX ."
b0000000000000001 /"
bXXXXXXXXXXXXXXXX 0"
01"
02"
U3"
U4"
bXXXXXXXXXXXXXXXX 5"
bUUUUUUUUUUUUUUUU 6"
bUUUUUUUUUUUUUUUU 7"
bUUUUUUUUUUUUUUUU 8"
bUUU 9"
U:"
U;"
U<"
U="
U>"
U?"
0@"
0A"
#30000000
1"
1/
b0000000000000000 G
b0000000000000000 I
b0000000000000000 J
1T
b0000000000000000 Z
b0000000000000000 [
b0000000000000000 \
b0000000000000000 b
b0000000000000000 g
b0000000000000000 k
b0000000000000000 '"
12"
b0000000000000000 6"
b0000000000000000 8"
#60000000
1!
0"
1.
0/
b0000000000000001 M
b0000000000000010 N
b0000000000000010 O
b0000000000000010 P
1S
0T
b0000000000000001 r
b0000000000000010 t
Zu
b0000000000000010 v
b0000000000000010 y
b0000000000000010 ""
b0000000000000010 $"
b0000000000000010 &"
b0000000000000010 ("
b0000000000000010 /"
11"
02"
#120000000
0!
0.
0S
01"
#180000000
1!
b1000100000000000 $
0%
1&
0'
1(
0)
X*
b100 -
1.
b1000100000000000 0
01
12
03
14
05
X6
b100 9
b010 :
b000 ;
b000 <
b0000000 =
b0000000000 >
b0000000000000000 ?
b0000000000000000 @
b0000000000000000 A
b0000000000000000 C
b0000000000000000 D
1E
b0000000000000000 F
b0000000000000000 H
b0000000000000010 J
b0000000000000000 K
b0000000000000010 M
b0000000000000011 N
b0000000000000011 O
b0000000000000011 P
b0000000000000011 Q
1S
0U
b000 V
b000 W
b010 X
b0000000000000000 Y
b0000000000000010 \
0]
b0000000000000000 ^
b0000000000000000 _
b0000000000000000 `
1a
b0000000000000000 c
b0000000000000000 d
b0000000000000000 f
b0000000000000010 g
b0000000000000000 h
1j
b0000000000000000 l
b0000000000000000 m
b0000000000000000 o
b0000000000000010 r
b0000000000000011 t
1u
b0000000000000011 v
b0000000000000011 y
b0000000000000000 z
b0000000000000011 {
b0000000000000011 }
b0000000000000011 ""
b0000000000000011 #"
b0000000000000011 $"
b0000000000000011 &"
b0000000000000011 ("
X)"
b0000000000000000 +"
b0000000000000000 ,"
b0000000000000000 ."
b0000000000000011 /"
b0000000000000000 0"
11"
13"
04"
b0000000000000000 5"
b0000000000000010 6"
b100 9"
0:"
1;"
0<"
1="
0>"
X?"
#240000000
0!
0.
0S
01"
#300000000
1!
b1011100000000000 $
1%
0(
1)
0*
b101 -
1.
b1011100000000000 0
11
04
15
06
b101 9
b110 :
b0000000000000010 C
b0000000000000010 D
b0000000000000000 J
b0000000000000010 L
b0000000000000011 M
b0000000000000100 N
b0000000000000100 O
b0000000000000100 P
b0000000000000100 Q
1S
1U
b110 X
b0000000000000010 Y
b0000000000000000 \
b0000000000000000 g
b0000000000000011 r
b0000000000000100 t
b0000000000000100 v
b0000000000000100 y
b0000000000000100 {
b0000000000000100 }
b0000000000000100 ""
b0000000000000100 #"
b0000000000000100 $"
b0000000000000100 &"
b0000000000000100 ("
0)"
b0000000000000010 *"
b0000000000000010 ,"
b0000000000000010 ."
b0000000000000100 /"
b0000000000000010 0"
11"
03"
14"
b0000000000000000 6"
b0000000000000010 7"
b0000000000000010 8"
b101 9"
1:"
0="
1>"
0?"
#360000000
0!
0.
0S
01"
#420000000
1!
b0001111100000010 $
0&
X'
0)
1*
b000 -
1.
b0001111100000010 0
02
X3
05
16
b000 9
b111 :
b110 ;
b010 <
b0000010 =
b1100000010 >
b0000000000000010 ?
b1111111100000010 @
b1111111100000010 A
b0000000000000100 C
b0000000000000100 D
0E
b0000000000000100 F
b0000000000000010 G
b0000000000000010 H
b0000000000000010 I
b0000000000000000 J
b0000000000000010 K
b0000000000000100 M
b0000000000000101 N
b0000000000000101 O
b0000000000000101 P
b1111111100000111 Q
1S
b110 V
b010 W
b111 X
b0000000000000100 Y
b0000000000000010 Z
b0000000000000010 [
b0000000000000000 \
X]
b0000000000000010 ^
b1111111100000010 _
b1111111100000010 `
0a
b0000000000000010 b
b1111111100000010 c
b0000000000000010 d
b0000000000000010 f
b0000000000000000 g
b0000000000000010 h
0j
b0000000000000010 k
b0000000000000010 l
b0000000000000100 m
Zn
b0000000000000100 o
b0000000000000100 r
b0000000000000101 t
b0000000000000101 v
b0000000000000101 y
b1111111100000010 z
b1111111100000111 {
b1111111100000111 }
b0000000000000101 ""
b1111111100000111 #"
b0000000000000101 $"
b0000000000000101 &"
b0000000000000010 '"
b0000000000000101 ("
1)"
b0000000000000100 +"
b0000000000000100 ,"
b0000000000000100 ."
b0000000000000101 /"
b0000000000000100 0"
11"
04"
b0000000000000100 5"
b0000000000000000 6"
b000 9"
0;"
X<"
0>"
1?"
#480000000
0!
0.
0S
01"
#540000000
1!
b1100001010010000 $
0%
0'
X*
1+
b110 -
1.
b1100001010010000 0
01
03
X6
17
b110 9
b000 :
b101 ;
b000 <
b0010000 =
b1010010000 >
b0000000000010000 ?
b1111111010010000 @
b0000000000010000 A
b0101 B
b0000000000000000 C
b0000000000000000 D
1E
b0000000000000000 F
b0000000000000000 G
b0000000000000000 H
b0000000000000000 I
b0000000000000000 J
b0000000000000000 K
b0000000000000101 M
b0000000000010110 N
b0000000000010110 O
b0000000000000110 P
b0000000000010110 Q
1R
1S
0U
b101 V
b000 W
b000 X
b0000000000000000 Y
b0000000000000000 Z
b0000000000000000 [
b0000000000000000 \
0]
b0000000000010000 ^
b1111111010010000 _
b0000000000010000 `
b0000000000000000 b
b0000000000010000 c
b0000000000000000 d
1e
b0000000000000000 f
b0000000000000000 g
b0000000000000000 h
b0101 i
1j
b0000000000000000 k
b0000000000000000 l
b0000000000000000 m
Zn
b0000000000000000 o
b0000000000000101 r
b0000000000000110 t
b0000000000000110 v
b0000000000000110 y
b0000000000010000 z
b0000000000010110 {
0|
b0000000000010110 }
1!"
b0000000000000110 ""
b0000000000010110 #"
b0000000000010110 $"
b0000000000010110 &"
b0000000000000000 '"
b0000000000010110 ("
X)"
b0000000000000000 +"
b0000000000000000 ,"
b0000000000000000 ."
b0000000000000110 /"
b0000000000000000 0"
11"
b0000000000000000 5"
b0000000000000000 6"
b110 9"
0:"
0<"
X?"
1@"
#600000000
0!
0.
0S
01"
#660000000
1!
b1110010000000000 $
1,
b111 -
1.
b1110010000000000 0
18
b111 9
b001 :
b000 ;
b0000000 =
b0000000000 >
b0000000000000000 ?
b0000000000000000 @
b0000000000000000 A
b0000 B
b0000000000000100 C
b0000000000010111 D
0E
b0000000000000100 F
b0000000000000100 J
b0000000000000100 K
b0000000000010110 M
b0000000000010111 N
b0000000000000000 O
b0000000000010111 P
b0000000000010111 Q
0R
1S
b000 V
b001 X
b0000000000010111 Y
b0000000000000100 \
b0000000000000000 ^
b0000000000000000 _
b0000000000000000 `
b0000000000000000 c
b0000000000000100 g
b0000000000000100 h
b0000 i
0j
b0000000000000100 l
b0000000000000100 m
0n
b0000000000000100 o
b0000000000010110 r
b0000000000010111 t
b0000000000010111 v
b0000000000010111 y
b0000000000000000 z
b0000000000010111 {
1|
b0000000000010111 }
0!"
b0000000000010111 ""
b0000000000010111 #"
b0000000000010111 $"
1%"
b0000000000010111 &"
b0000000000000000 ("
b0000000000000100 +"
b0000000000000100 ,"
1-"
b0000000000000100 ."
b0000000000010111 /"
b0000000000010111 0"
11"
b0000000000000100 5"
b0000000000000100 6"
b111 9"
1A"
#720000000
0!
0.
0S
01"
